eia/__init__.py
eia/client.py
python_eia-0.1.0.dist-info/METADATA
python_eia-0.1.0.dist-info/WHEEL
python_eia-0.1.0.dist-info/RECORD
